frogsay/__init__.py
frogsay/client.py
frogsay/speech.py
frogsay/version.py
frogsay-2.0.0.dist-info/DESCRIPTION.rst
frogsay-2.0.0.dist-info/METADATA
frogsay-2.0.0.dist-info/RECORD
frogsay-2.0.0.dist-info/WHEEL
frogsay-2.0.0.dist-info/entry_points.txt
frogsay-2.0.0.dist-info/metadata.json
frogsay-2.0.0.dist-info/top_level.txt
