Metadata-Version: 2.0
Name: frogsay
Version: 2.0.0
Summary: An ASCII frog prints a handy FROG tip on the command line.
Home-page: https://github.com/clibc/frogsay
Author: Charlie Liban
Author-email: charlie@clib.ca
License: MIT
Requires-Dist: click (==6.2)
Requires-Dist: python-RIBBIT (==1.0.2.dev0)
Requires-Dist: semidbm (==0.5.1)
Requires-Dist: six (==1.10.0)
